{
    "JAL328H1-S-20179": {
        "courseId": "11740",
        "org": "LIN",
        "orgName": "Linguistics (LIN) (JLP) (JLS) (JAL) (JFL) (ARH)",
        "courseTitle": "Writing Systems",
        "code": "JAL328H1",
        "courseDescription": "Introduction to writing systems; their historical development, their relationship to language, and their role in culture and society. (Given by the Departments of Anthropology and Linguistics) (Not offered every year)",
        "prerequisite": "ANT100Y1/LIN101H1/LIN200H1",
        "corequisite": "",
        "exclusion": "",
        "recommendedPreparation": "",
        "section": "S",
        "session": "20179",
        "webTimetableInstructions": "",
        "deliveryInstructions": null,
        "breadthCategories": "Thought, Belief and Behaviour (2)",
        "distributionCategories": "Social Science",
        "meetings": {
            "LEC-5101": {
                "schedule": {
                    "TH-80471": {
                        "meetingDay": "TH",
                        "meetingStartTime": "18:00",
                        "meetingEndTime": "21:00",
                        "meetingScheduleId": "80471",
                        "assignedRoom1": null,
                        "assignedRoom2": "LM 161"
                    }
                },
                "instructors": {
                    "2416123": {
                        "instructorId": "2416123",
                        "firstName": "R",
                        "lastName": "Craioveanu"
                    }
                },
                "meetingId": "18537",
                "teachingMethod": "LEC",
                "sectionNumber": "5101",
                "subtitle": "",
                "cancel": "",
                "waitlist": "Y",
                "deliveryMode": "CLASS",
                "online": "In Person",
                "enrollmentCapacity": "125",
                "actualEnrolment": "105",
                "actualWaitlist": "0",
                "enrollmentIndicator": "P",
                "meetingStatusNotes": "",
                "enrollmentControls": [
                    {
                        "postId": null,
                        "postCode": null,
                        "postName": null,
                        "subjectId": "46",
                        "subjectCode": "LIN",
                        "subjectName": "LINGUISTICS",
                        "designationId": "2",
                        "designationCode": "MAJ",
                        "designationName": "Major",
                        "yearOfStudy": "*",
                        "typeOfProgramId": null,
                        "typeOfProgramCode": null,
                        "typeOfProgramName": null,
                        "primaryOrgId": "6",
                        "primaryOrgCode": "ARTSC",
                        "primaryOrgName": "Faculty of Arts and Science",
                        "secondaryOrgId": "1",
                        "secondaryOrgCode": "*",
                        "secondaryOrgName": "",
                        "assocOrgId": "1",
                        "assocOrgCode": "*",
                        "assocOrgName": "",
                        "adminOrgId": "1",
                        "adminOrgCode": "*",
                        "adminOrgName": ""
                    },
                    {
                        "postId": null,
                        "postCode": null,
                        "postName": null,
                        "subjectId": "46",
                        "subjectCode": "LIN",
                        "subjectName": "LINGUISTICS",
                        "designationId": "5",
                        "designationCode": "SPE",
                        "designationName": "Specialist",
                        "yearOfStudy": "*",
                        "typeOfProgramId": null,
                        "typeOfProgramCode": null,
                        "typeOfProgramName": null,
                        "primaryOrgId": "6",
                        "primaryOrgCode": "ARTSC",
                        "primaryOrgName": "Faculty of Arts and Science",
                        "secondaryOrgId": "1",
                        "secondaryOrgCode": "*",
                        "secondaryOrgName": "",
                        "assocOrgId": "1",
                        "assocOrgCode": "*",
                        "assocOrgName": "",
                        "adminOrgId": "1",
                        "adminOrgCode": "*",
                        "adminOrgName": ""
                    },
                    {
                        "postId": null,
                        "postCode": null,
                        "postName": null,
                        "subjectId": "46",
                        "subjectCode": "LIN",
                        "subjectName": "LINGUISTICS",
                        "designationId": "2",
                        "designationCode": "MAJ",
                        "designationName": "Major",
                        "yearOfStudy": "*",
                        "typeOfProgramId": null,
                        "typeOfProgramCode": null,
                        "typeOfProgramName": null,
                        "primaryOrgId": "5",
                        "primaryOrgCode": "ARCLA",
                        "primaryOrgName": "John H. Daniels Faculty of Architecture, Landscape, & Design",
                        "secondaryOrgId": "1",
                        "secondaryOrgCode": "*",
                        "secondaryOrgName": "",
                        "assocOrgId": "1",
                        "assocOrgCode": "*",
                        "assocOrgName": "",
                        "adminOrgId": "1",
                        "adminOrgCode": "*",
                        "adminOrgName": ""
                    },
                    {
                        "postId": null,
                        "postCode": null,
                        "postName": null,
                        "subjectId": "46",
                        "subjectCode": "LIN",
                        "subjectName": "LINGUISTICS",
                        "designationId": "5",
                        "designationCode": "SPE",
                        "designationName": "Specialist",
                        "yearOfStudy": "*",
                        "typeOfProgramId": null,
                        "typeOfProgramCode": null,
                        "typeOfProgramName": null,
                        "primaryOrgId": "5",
                        "primaryOrgCode": "ARCLA",
                        "primaryOrgName": "John H. Daniels Faculty of Architecture, Landscape, & Design",
                        "secondaryOrgId": "1",
                        "secondaryOrgCode": "*",
                        "secondaryOrgName": "",
                        "assocOrgId": "1",
                        "assocOrgCode": "*",
                        "assocOrgName": "",
                        "adminOrgId": "1",
                        "adminOrgCode": "*",
                        "adminOrgName": ""
                    },
                    {
                        "postId": "332",
                        "postCode": "ASSPE1681",
                        "postName": "SP LINGUISTICS & GERMAN",
                        "subjectId": null,
                        "subjectCode": null,
                        "subjectName": null,
                        "designationId": null,
                        "designationCode": null,
                        "designationName": null,
                        "yearOfStudy": "*",
                        "typeOfProgramId": null,
                        "typeOfProgramCode": null,
                        "typeOfProgramName": null,
                        "primaryOrgId": null,
                        "primaryOrgCode": null,
                        "primaryOrgName": null,
                        "secondaryOrgId": null,
                        "secondaryOrgCode": null,
                        "secondaryOrgName": null,
                        "assocOrgId": null,
                        "assocOrgCode": null,
                        "assocOrgName": null,
                        "adminOrgId": null,
                        "adminOrgCode": null,
                        "adminOrgName": null
                    }
                ]
            }
        }
    },
    "JAL401H1-F-20179": {
        "courseId": "11743",
        "org": "LIN",
        "orgName": "Linguistics (LIN) (JLP) (JLS) (JAL) (JFL) (ARH)",
        "courseTitle": "Field Linguistics",
        "code": "JAL401H1",
        "courseDescription": "Practice in language analysis based on elicited data from a native speaker of a foreign language, emphasizing procedures and techniques. (Given by the Departments of Anthropology and Linguistics)",
        "prerequisite": "Completion of LIN322H1 and LIN331H1 or permission of the instructor",
        "corequisite": "",
        "exclusion": "",
        "recommendedPreparation": "",
        "section": "F",
        "session": "20179",
        "webTimetableInstructions": "",
        "deliveryInstructions": null,
        "breadthCategories": "Thought, Belief and Behaviour (2)",
        "distributionCategories": "Social Science",
        "meetings": {
            "LEC-0101": {
                "schedule": {
                    "MO-84526": {
                        "meetingDay": "MO",
                        "meetingStartTime": "16:00",
                        "meetingEndTime": "18:00",
                        "meetingScheduleId": "84526",
                        "assignedRoom1": "SS 2125",
                        "assignedRoom2": null
                    },
                    "WE-84527": {
                        "meetingDay": "WE",
                        "meetingStartTime": "16:00",
                        "meetingEndTime": "18:00",
                        "meetingScheduleId": "84527",
                        "assignedRoom1": "SS 2125",
                        "assignedRoom2": null
                    }
                },
                "instructors": {
                    "2416124": {
                        "instructorId": "2416124",
                        "firstName": "G",
                        "lastName": "Thomas"
                    }
                },
                "meetingId": "18538",
                "teachingMethod": "LEC",
                "sectionNumber": "0101",
                "subtitle": "",
                "cancel": "",
                "waitlist": "Y",
                "deliveryMode": "CLASS",
                "online": "In Person",
                "enrollmentCapacity": "15",
                "actualEnrolment": "15",
                "actualWaitlist": "0",
                "enrollmentIndicator": "P",
                "meetingStatusNotes": "",
                "enrollmentControls": [
                    {
                        "postId": null,
                        "postCode": null,
                        "postName": null,
                        "subjectId": "46",
                        "subjectCode": "LIN",
                        "subjectName": "LINGUISTICS",
                        "designationId": "2",
                        "designationCode": "MAJ",
                        "designationName": "Major",
                        "yearOfStudy": "*",
                        "typeOfProgramId": "1",
                        "typeOfProgramCode": "*",
                        "typeOfProgramName": "All Types",
                        "primaryOrgId": "6",
                        "primaryOrgCode": "ARTSC",
                        "primaryOrgName": "Faculty of Arts and Science",
                        "secondaryOrgId": "1",
                        "secondaryOrgCode": "*",
                        "secondaryOrgName": "",
                        "assocOrgId": "1",
                        "assocOrgCode": "*",
                        "assocOrgName": "",
                        "adminOrgId": "1",
                        "adminOrgCode": "*",
                        "adminOrgName": ""
                    },
                    {
                        "postId": null,
                        "postCode": null,
                        "postName": null,
                        "subjectId": "46",
                        "subjectCode": "LIN",
                        "subjectName": "LINGUISTICS",
                        "designationId": "5",
                        "designationCode": "SPE",
                        "designationName": "Specialist",
                        "yearOfStudy": "*",
                        "typeOfProgramId": "1",
                        "typeOfProgramCode": "*",
                        "typeOfProgramName": "All Types",
                        "primaryOrgId": "6",
                        "primaryOrgCode": "ARTSC",
                        "primaryOrgName": "Faculty of Arts and Science",
                        "secondaryOrgId": "1",
                        "secondaryOrgCode": "*",
                        "secondaryOrgName": "",
                        "assocOrgId": "1",
                        "assocOrgCode": "*",
                        "assocOrgName": "",
                        "adminOrgId": "1",
                        "adminOrgCode": "*",
                        "adminOrgName": ""
                    },
                    {
                        "postId": null,
                        "postCode": null,
                        "postName": null,
                        "subjectId": "46",
                        "subjectCode": "LIN",
                        "subjectName": "LINGUISTICS",
                        "designationId": "2",
                        "designationCode": "MAJ",
                        "designationName": "Major",
                        "yearOfStudy": "*",
                        "typeOfProgramId": null,
                        "typeOfProgramCode": null,
                        "typeOfProgramName": null,
                        "primaryOrgId": "5",
                        "primaryOrgCode": "ARCLA",
                        "primaryOrgName": "John H. Daniels Faculty of Architecture, Landscape, & Design",
                        "secondaryOrgId": "1",
                        "secondaryOrgCode": "*",
                        "secondaryOrgName": "",
                        "assocOrgId": "1",
                        "assocOrgCode": "*",
                        "assocOrgName": "",
                        "adminOrgId": "1",
                        "adminOrgCode": "*",
                        "adminOrgName": ""
                    },
                    {
                        "postId": null,
                        "postCode": null,
                        "postName": null,
                        "subjectId": "46",
                        "subjectCode": "LIN",
                        "subjectName": "LINGUISTICS",
                        "designationId": "5",
                        "designationCode": "SPE",
                        "designationName": "Specialist",
                        "yearOfStudy": "*",
                        "typeOfProgramId": null,
                        "typeOfProgramCode": null,
                        "typeOfProgramName": null,
                        "primaryOrgId": "5",
                        "primaryOrgCode": "ARCLA",
                        "primaryOrgName": "John H. Daniels Faculty of Architecture, Landscape, & Design",
                        "secondaryOrgId": "1",
                        "secondaryOrgCode": "*",
                        "secondaryOrgName": "",
                        "assocOrgId": "1",
                        "assocOrgCode": "*",
                        "assocOrgName": "",
                        "adminOrgId": "1",
                        "adminOrgCode": "*",
                        "adminOrgName": ""
                    },
                    {
                        "postId": "332",
                        "postCode": "ASSPE1681",
                        "postName": "SP LINGUISTICS & GERMAN",
                        "subjectId": null,
                        "subjectCode": null,
                        "subjectName": null,
                        "designationId": null,
                        "designationCode": null,
                        "designationName": null,
                        "yearOfStudy": "*",
                        "typeOfProgramId": null,
                        "typeOfProgramCode": null,
                        "typeOfProgramName": null,
                        "primaryOrgId": null,
                        "primaryOrgCode": null,
                        "primaryOrgName": null,
                        "secondaryOrgId": null,
                        "secondaryOrgCode": null,
                        "secondaryOrgName": null,
                        "assocOrgId": null,
                        "assocOrgCode": null,
                        "assocOrgName": null,
                        "adminOrgId": null,
                        "adminOrgCode": null,
                        "adminOrgName": null
                    }
                ]
            },
            "LEC-5101": {
                "schedule": {
                    "MO-95384": {
                        "meetingDay": "MO",
                        "meetingStartTime": "18:30",
                        "meetingEndTime": "20:30",
                        "meetingScheduleId": "95384",
                        "assignedRoom1": "BL 113",
                        "assignedRoom2": null
                    },
                    "WE-95385": {
                        "meetingDay": "WE",
                        "meetingStartTime": "16:00",
                        "meetingEndTime": "18:00",
                        "meetingScheduleId": "95385",
                        "assignedRoom1": "BL 113",
                        "assignedRoom2": null
                    }
                },
                "instructors": {
                    "2416125": {
                        "instructorId": "2416125",
                        "firstName": "S",
                        "lastName": "Oliveira de Lima"
                    }
                },
                "meetingId": "27194",
                "teachingMethod": "LEC",
                "sectionNumber": "5101",
                "subtitle": "",
                "cancel": "",
                "waitlist": "Y",
                "deliveryMode": "CLASS",
                "online": "In Person",
                "enrollmentCapacity": "10",
                "actualEnrolment": "5",
                "actualWaitlist": "0",
                "enrollmentIndicator": "P",
                "meetingStatusNotes": "Added: Aug 14, 2017",
                "enrollmentControls": [
                    {
                        "postId": null,
                        "postCode": null,
                        "postName": null,
                        "subjectId": "46",
                        "subjectCode": "LIN",
                        "subjectName": "LINGUISTICS",
                        "designationId": "2",
                        "designationCode": "MAJ",
                        "designationName": "Major",
                        "yearOfStudy": "*",
                        "typeOfProgramId": "1",
                        "typeOfProgramCode": "*",
                        "typeOfProgramName": "All Types",
                        "primaryOrgId": "6",
                        "primaryOrgCode": "ARTSC",
                        "primaryOrgName": "Faculty of Arts and Science",
                        "secondaryOrgId": "1",
                        "secondaryOrgCode": "*",
                        "secondaryOrgName": "",
                        "assocOrgId": "1",
                        "assocOrgCode": "*",
                        "assocOrgName": "",
                        "adminOrgId": "1",
                        "adminOrgCode": "*",
                        "adminOrgName": ""
                    },
                    {
                        "postId": null,
                        "postCode": null,
                        "postName": null,
                        "subjectId": "46",
                        "subjectCode": "LIN",
                        "subjectName": "LINGUISTICS",
                        "designationId": "5",
                        "designationCode": "SPE",
                        "designationName": "Specialist",
                        "yearOfStudy": "*",
                        "typeOfProgramId": "1",
                        "typeOfProgramCode": "*",
                        "typeOfProgramName": "All Types",
                        "primaryOrgId": "6",
                        "primaryOrgCode": "ARTSC",
                        "primaryOrgName": "Faculty of Arts and Science",
                        "secondaryOrgId": "1",
                        "secondaryOrgCode": "*",
                        "secondaryOrgName": "",
                        "assocOrgId": "1",
                        "assocOrgCode": "*",
                        "assocOrgName": "",
                        "adminOrgId": "1",
                        "adminOrgCode": "*",
                        "adminOrgName": ""
                    },
                    {
                        "postId": null,
                        "postCode": null,
                        "postName": null,
                        "subjectId": "46",
                        "subjectCode": "LIN",
                        "subjectName": "LINGUISTICS",
                        "designationId": "2",
                        "designationCode": "MAJ",
                        "designationName": "Major",
                        "yearOfStudy": "*",
                        "typeOfProgramId": null,
                        "typeOfProgramCode": null,
                        "typeOfProgramName": null,
                        "primaryOrgId": "5",
                        "primaryOrgCode": "ARCLA",
                        "primaryOrgName": "John H. Daniels Faculty of Architecture, Landscape, & Design",
                        "secondaryOrgId": "1",
                        "secondaryOrgCode": "*",
                        "secondaryOrgName": "",
                        "assocOrgId": "1",
                        "assocOrgCode": "*",
                        "assocOrgName": "",
                        "adminOrgId": "1",
                        "adminOrgCode": "*",
                        "adminOrgName": ""
                    },
                    {
                        "postId": null,
                        "postCode": null,
                        "postName": null,
                        "subjectId": "46",
                        "subjectCode": "LIN",
                        "subjectName": "LINGUISTICS",
                        "designationId": "5",
                        "designationCode": "SPE",
                        "designationName": "Specialist",
                        "yearOfStudy": "*",
                        "typeOfProgramId": null,
                        "typeOfProgramCode": null,
                        "typeOfProgramName": null,
                        "primaryOrgId": "5",
                        "primaryOrgCode": "ARCLA",
                        "primaryOrgName": "John H. Daniels Faculty of Architecture, Landscape, & Design",
                        "secondaryOrgId": "1",
                        "secondaryOrgCode": "*",
                        "secondaryOrgName": "",
                        "assocOrgId": "1",
                        "assocOrgCode": "*",
                        "assocOrgName": "",
                        "adminOrgId": "1",
                        "adminOrgCode": "*",
                        "adminOrgName": ""
                    }
                ]
            }
        }
    }
}